README.rst
setup.cfg
setup.py
miproman/__init__.py
miproman/argument_parser.py
miproman/config_parser.py
miproman/settings.py
miproman.egg-info/PKG-INFO
miproman.egg-info/SOURCES.txt
miproman.egg-info/dependency_links.txt
miproman.egg-info/entry_points.txt
miproman.egg-info/requires.txt
miproman.egg-info/top_level.txt
miproman.egg-info/zip-safe