Metadata-Version: 1.0
Name: miproman
Version: 0.1
Summary: Easy iTerm2 Profiles For Everyone!
Home-page: https://github.com/jatinn/miproman
Author: Jatin Nagpal
Author-email: jatinn@outlook.com
License: Apache License 2.0
Download-URL: https://github.com/jatinn/miproman/tarball/0.1
Platform: UNKNOWN
Classifier: Development Status :: 4 - Beta
Classifier: Intended Audience :: Developers
Classifier: Intended Audience :: System Administrators
Classifier: License :: OSI Approved :: Apache Software License
Classifier: Natural Language :: English
Classifier: Programming Language :: Python
Classifier: Topic :: Internet
Classifier: Topic :: Software Development
Classifier: Topic :: Terminals
Classifier: Topic :: System
Classifier: Topic :: Utilities
